Pyriod/Pyriod.py
Pyriod/__init__.py
Pyriod/pyquist.py
Pyriod/docs/Periodogram.md
Pyriod/docs/Signals.md
Pyriod/docs/TimeSeries.md
Pyriod-0.3.3.dist-info/LICENSE
Pyriod-0.3.3.dist-info/METADATA
Pyriod-0.3.3.dist-info/WHEEL
Pyriod-0.3.3.dist-info/top_level.txt
Pyriod-0.3.3.dist-info/RECORD
