Metadata-Version: 2.1
Name: Pyriod
Version: 0.3.3
Summary: Basic period detection and fitting routines for astronomical time series.
Home-page: https://github.com/keatonb/Pyriod
Author: Keaton Bell
Author-email: keatonbell@utexas.edu
Classifier: Development Status :: 4 - Beta
Classifier: Programming Language :: Python
Classifier: License :: OSI Approved :: GNU General Public License (GPL)
Classifier: Operating System :: OS Independent
Requires-Python: >=3.6
License-File: LICENSE
Requires-Dist: numpy>=1.11
Requires-Dist: pandas>=1.0
Requires-Dist: scipy>=0.19
Requires-Dist: astropy
Requires-Dist: lightkurve>=2.1.1
Requires-Dist: lmfit>=1.0
Requires-Dist: beautifulsoup4>=4.11
Requires-Dist: matplotlib>=3.4
Requires-Dist: ipympl>=0.7
Requires-Dist: ipywidgets>=8
Requires-Dist: qgridnext>1.3.1
Requires-Dist: ipyfilechooser>=0.3.5
